<archimate:ArchimateDiagramModel
    xmlns:xsi="http://www.w3.org/2001/XMLSchema-instance"
    xmlns:archimate="http://www.archimatetool.com/archimate"
    name="Relacion de dependencia de Sconing con process Server"
    id="5456dcb3">
  <children
      xsi:type="archimate:DiagramModelArchimateObject"
      id="48e4cf12">
    <bounds
        x="372"
        y="84"
        width="406"
        height="404"/>
    <children
        xsi:type="archimate:DiagramModelArchimateObject"
        id="fa26d3f2">
      <bounds
          x="72"
          y="144"
          width="271"
          height="97"/>
      <children
          xsi:type="archimate:DiagramModelArchimateObject"
          id="3ba7a39f"
          targetConnections="273671b6">
        <bounds
            x="24"
            y="24"
            width="229"
            height="25"/>
        <archimateElement
            xsi:type="archimate:ApplicationInterface"
            href="ApplicationInterface_99a4ab7c.xml#99a4ab7c"/>
      </children>
      <children
          xsi:type="archimate:DiagramModelArchimateObject"
          id="b1ec73de"
          targetConnections="6730d5e4">
        <bounds
            x="24"
            y="60"
            width="229"
            height="25"/>
        <archimateElement
            xsi:type="archimate:ApplicationInterface"
            href="ApplicationInterface_c1812de2.xml#c1812de2"/>
      </children>
      <archimateElement
          xsi:type="archimate:ApplicationService"
          href="ApplicationService_4897453d.xml#4897453d"/>
    </children>
    <children
        xsi:type="archimate:DiagramModelArchimateObject"
        id="0c3f6ac5">
      <bounds
          x="71"
          y="252"
          width="273"
          height="97"/>
      <children
          xsi:type="archimate:DiagramModelArchimateObject"
          id="7129059c"
          targetConnections="09729fdf">
        <bounds
            x="24"
            y="24"
            width="229"
            height="25"/>
        <archimateElement
            xsi:type="archimate:ApplicationInterface"
            href="ApplicationInterface_3cf55f87.xml#3cf55f87"/>
      </children>
      <children
          xsi:type="archimate:DiagramModelArchimateObject"
          id="15938a72"
          targetConnections="18600bef">
        <bounds
            x="24"
            y="60"
            width="229"
            height="25"/>
        <archimateElement
            xsi:type="archimate:ApplicationInterface"
            href="ApplicationInterface_a420a09f.xml#a420a09f"/>
      </children>
      <archimateElement
          xsi:type="archimate:ApplicationService"
          href="ApplicationService_89ad9a11.xml#89ad9a11"/>
    </children>
    <children
        xsi:type="archimate:DiagramModelArchimateObject"
        id="2064031b">
      <bounds
          x="72"
          y="72"
          width="272"
          height="61"/>
      <children
          xsi:type="archimate:DiagramModelArchimateObject"
          id="c5a76150"
          targetConnections="c6010910">
        <bounds
            x="24"
            y="24"
            width="229"
            height="25"/>
        <archimateElement
            xsi:type="archimate:ApplicationInterface"
            href="ApplicationInterface_00bc142c.xml#00bc142c"/>
      </children>
      <archimateElement
          xsi:type="archimate:ApplicationService"
          href="ApplicationService_72af43d0.xml#72af43d0"/>
    </children>
    <archimateElement
        xsi:type="archimate:ApplicationComponent"
        href="ApplicationComponent_12a26ec6.xml#12a26ec6"/>
  </children>
  <children
      xsi:type="archimate:DiagramModelArchimateObject"
      id="41d11e92">
    <sourceConnections
        xsi:type="archimate:DiagramModelArchimateConnection"
        id="273671b6"
        source="41d11e92"
        target="3ba7a39f">
      <archimateRelationship
          xsi:type="archimate:ServingRelationship"
          href="ServingRelationship_9d0f285e.xml#9d0f285e"/>
    </sourceConnections>
    <sourceConnections
        xsi:type="archimate:DiagramModelArchimateConnection"
        id="6730d5e4"
        source="41d11e92"
        target="b1ec73de">
      <archimateRelationship
          xsi:type="archimate:ServingRelationship"
          href="ServingRelationship_7bc0a92c.xml#7bc0a92c"/>
    </sourceConnections>
    <sourceConnections
        xsi:type="archimate:DiagramModelArchimateConnection"
        id="09729fdf"
        source="41d11e92"
        target="7129059c">
      <archimateRelationship
          xsi:type="archimate:ServingRelationship"
          href="ServingRelationship_e561356f.xml#e561356f"/>
    </sourceConnections>
    <sourceConnections
        xsi:type="archimate:DiagramModelArchimateConnection"
        id="18600bef"
        source="41d11e92"
        target="15938a72">
      <archimateRelationship
          xsi:type="archimate:ServingRelationship"
          href="ServingRelationship_e35775b8.xml#e35775b8"/>
    </sourceConnections>
    <sourceConnections
        xsi:type="archimate:DiagramModelArchimateConnection"
        id="c6010910"
        source="41d11e92"
        target="c5a76150">
      <archimateRelationship
          xsi:type="archimate:ServingRelationship"
          href="ServingRelationship_ee5f94e3.xml#ee5f94e3"/>
    </sourceConnections>
    <bounds
        x="180"
        y="156"
        width="97"
        height="301"/>
    <archimateElement
        xsi:type="archimate:ApplicationComponent"
        href="ApplicationComponent_8d046ea9.xml#8d046ea9"/>
  </children>
</archimate:ArchimateDiagramModel>
